codemos/__init__.py
codemos/main.py
codemos-0.1.2.dist-info/entry_points.txt
codemos-0.1.2.dist-info/WHEEL
codemos-0.1.2.dist-info/METADATA
codemos-0.1.2.dist-info/RECORD
