Metadata-Version: 2.1
Name: codemos
Version: 0.1.2
Summary: 
Author: Nathanaël
Author-email: roipoussiere@protonmail.com
Requires-Python: >=3.8,<4.0
Classifier: Programming Language :: Python :: 3
Classifier: Programming Language :: Python :: 3.8
Classifier: Programming Language :: Python :: 3.9
Requires-Dist: Jinja2 (>=3.0.1,<4.0.0)
Requires-Dist: aiofiles (>=0.7.0,<0.8.0)
Requires-Dist: appdirs (>=1.4.4,<2.0.0)
Requires-Dist: fastapi (>=0.65.2,<0.66.0)
Requires-Dist: python-dotenv (>=0.18.0,<0.19.0)
Requires-Dist: requests (>=2.25.1,<3.0.0)
Requires-Dist: uvicorn (>=0.14.0,<0.15.0)
